Workbook

Sheet 0. Guía
B1: Guía de Usuario — Calculadora de Proyección de Servicios
B3: Objetivo
B4: Este archivo distribuye un Presupuesto Total anual entre 9 unidades de negocio (6 base + 3 comodines), ajustado por Benchmarks de Mercado, Estacionalidad de Ventas y reglas fiscales/operativas (SAT).
B6: Paso a paso
B7: 1) Ve a la pestaña '1. Configuración' y captura: Nombre del Cliente, Venta Anual Proyectada y Presupuesto Total a Contratar.
B8: 2) Ajusta (si aplica) la tabla de Benchmarks de Mercado. Elige un % por servicio (dentro del rango sugerido).
B9: 3) Activa/Desactiva servicios con el selector Sí/No. Solo los servicios activos participan en el cálculo.
B10: 4) Ve a '2. Estacionalidad' e ingresa la venta mensual proyectada (12 meses).
B11: 5) Revisa la '3. Matriz Proyección' para ver: (a) distribución anual por servicio, (b) montos mensuales ajustados por estacionalidad (FE), y (c) cálculo de Comisiones como % directo de la venta mensual.
B12: 6) En '4. Facturación' completa los campos manuales por servicio: Concepto del servicio y Clave/Concepto SAT. Los montos mensuales están vinculados automáticamente a la Matriz.
B13: 7) En '5. Dashboard' revisa el resumen y el gráfico (áreas apiladas + línea de ventas).
B16: Cálculo del Factor de Estacionalidad (FE)
... B27: Celdas de resultado (fórmulas)

Sheet 1. Configuración
B1: Configuración (Inputs)
B3: Nombre del Cliente | C3: Acme SA de CV
B4: Venta Anual Proyectada | C4: 50000000
B5: Presupuesto Total a Contratar | C5: 30000000
B6: Industria (texto libre) | C6: Ejemplo: Servicios Profesionales
B7: Tasa de Comisión (industria) | C7: 0.02
B9: Benchmarks de Mercado (Editable)
B11: Servicio | C11: Tipo | D11: Mín % | E11: Máx % | F11: % Elegido | G11: Activo (Sí/No)
B12: Legal | C12: Base | D12: 0.01 | E12: 0.03 | F12: =IF(AND(D12<>"",E12<>""),(D12+E12)/2,"") -> 0.02 | G12: Sí
B13: Contable | C13: Base | D13: 0.02 | E13: 0.04 | F13: =IF(AND(D13<>"",E13<>""),(D13+E13)/2,"") -> 0.03 | G13: Sí
B14: TI | C14: Base | D14: 0.04 | E14: 0.07 | F14: =IF(AND(D14<>"",E14<>""),(D14+E14)/2,"") -> 0.055 | G14: Sí
B15: Marketing | C15: Base | D15: 0.1 | E15: 0.15 | F15: =IF(AND(D15<>"",E15<>""),(D15+E15)/2,"") -> 0.125 | G15: Sí
B16: RH | C16: Base | D16: 0.03 | E16: 0.05 | F16: =IF(AND(D16<>"",E16<>""),(D16+E16)/2,"") -> 0.04 | G16: Sí
B17: Admin | C17: Base | D17: 0.03 | E17: 0.05 | F17: =IF(AND(D17<>"",E17<>""),(D17+E17)/2,"") -> 0.04 | G17: Sí
B18: Comisiones | C18: Comodín | F18: =C7 -> 0.02 | G18: Sí
B19: Logística | C19: Comodín | D19: 0.04 | E19: 0.08 | F19: =IF(AND(D19<>"",E19<>""),(D19+E19)/2,"") -> 0.06 | G19: No
B20: Construcción | C20: Comodín | D20: 0.02 | E20: 0.05 | F20: =IF(AND(D20<>"",E20<>""),(D20+E20)/2,"") -> 0.035 | G20: No
B22: Notas:
B23: • Puedes editar rangos y % elegido. • Activa/Desactiva servicios con Sí/No. • Comisiones usa la tasa de C7.

Sheet 2. Estacionalidad
B1: Curva de Estacionalidad (Ventas + FE)
B3: Venta anual (de Configuración) | C3: ='1. Configuración'!C4 -> 50000000
B4: Venta mensual promedio (Venta anual / 12) | C4: =C3/12 -> 4166666.7
B6: Mes | C6: Venta mensual proyectada | D6: FE | E6: Temporada
B7: Ene | C7: =$C$3/12 -> 4166666.7 | D7: =IFERROR(C7/$C$4,0) -> 1 | E7: =IF(D7>1,"Alta",IF(D7<1,"Baja","Media")) -> Media
B8: Feb | C8: =$C$3/12 -> 4166666.7 | D8: =IFERROR(C8/$C$4,0) -> 1 | E8: =IF(D8>1,"Alta",IF(D8<1,"Baja","Media")) -> Media
B9: Mar | C9: =$C$3/12 -> 4166666.7 | D9: =IFERROR(C9/$C$4,0) -> 1 | E9: =IF(D9>1,"Alta",IF(D9<1,"Baja","Media")) -> Media
B10: Abr | C10: =$C$3/12 -> 4166666.7 | D10: =IFERROR(C10/$C$4,0) -> 1 | E10: =IF(D10>1,"Alta",IF(D10<1,"Baja","Media")) -> Media
B11: May | C11: =$C$3/12 -> 4166666.7 | D11: =IFERROR(C11/$C$4,0) -> 1 | E11: =IF(D11>1,"Alta",IF(D11<1,"Baja","Media")) -> Media
B12: Jun | C12: =$C$3/12 -> 4166666.7 | D12: =IFERROR(C12/$C$4,0) -> 1 | E12: =IF(D12>1,"Alta",IF(D12<1,"Baja","Media")) -> Media
B13: Jul | C13: =$C$3/12 -> 4166666.7 | D13: =IFERROR(C13/$C$4,0) -> 1 | E13: =IF(D13>1,"Alta",IF(D13<1,"Baja","Media")) -> Media
B14: Ago | C14: =$C$3/12 -> 4166666.7 | D14: =IFERROR(C14/$C$4,0) -> 1 | E14: =IF(D14>1,"Alta",IF(D14<1,"Baja","Media")) -> Media
B15: Sep | C15: =$C$3/12 -> 4166666.7 | D15: =IFERROR(C15/$C$4,0) -> 1 | E15: =IF(D15>1,"Alta",IF(D15<1,"Baja","Media")) -> Media
B16: Oct | C16: =$C$3/12 -> 4166666.7 | D16: =IFERROR(C16/$C$4,0) -> 1 | E16: =IF(D16>1,"Alta",IF(D16<1,"Baja","Media")) -> Media
B17: Nov | C17: =$C$3/12 -> 4166666.7 | D17: =IFERROR(C17/$C$4,0) -> 1 | E17: =IF(D17>1,"Alta",IF(D17<1,"Baja","Media")) -> Media
B18: Dic | C18: =$C$3/12 -> 4166666.7 | D18: =IFERROR(C18/$C$4,0) -> 1 | E18: =IF(D18>1,"Alta",IF(D18<1,"Baja","Media")) -> Media
B20: Tip: | C20: Puedes pegar aquí tu distribución mensual real/proyectada; el FE se recalcula automáticamente.

Sheet 3. Matriz Proyección
B1: Matriz de Proyección (Cálculos)
B3: Presupuesto total anual | C3: ='1. Configuración'!C5 -> 30000000 | E3: Comisiones anuales (calculadas) | F3: =SUM('2. Estacionalidad'!C7:C18)*'1. Configuración'!C7 -> 1000000 | H3: Alerta | I3: =IF(F3>C3,"⚠ Comisiones exceden presupuesto","")
B4: Venta anual | C4: ='1. Configuración'!C4 -> 50000000 | E4: Presupuesto restante (sin comisiones) | F4: =MAX(C3-F3,0) -> 29000000
B5: Tasa comisión | C5: ='1. Configuración'!C7 -> 0.02
B7: Servicio | C7: Activo | D7: % Elegido | E7: Peso (solo activos) | F7: Asignación anual | G7: Asignación mensual base
B8: ='1. Configuración'!B12 -> Legal | C8: ='1. Configuración'!G12 -> Sí | D8: ='1. Configuración'!F12 -> 0.02 | E8: =IF(AND(C8="Sí",B8<>"Comisiones"),D8,0) -> 0.02 | F8: =IF(B8="Comisiones",$F$3,IF($C$17=0,0,$F$4*(E8/$C$17))) -> 1870967.7 | G8: =F8/12 -> 155913.98
B9: ='1. Configuración'!B13 -> Contable | C9: ='1. Configuración'!G13 -> Sí | D9: ='1. Configuración'!F13 -> 0.03 | E9: =IF(AND(C9="Sí",B9<>"Comisiones"),D9,0) -> 0.03 | F9: =IF(B9="Comisiones",$F$3,IF($C$17=0,0,$F$4*(E9/$C$17))) -> 2806451.6 | G9: =F9/12 -> 233870.97
B10: ='1. Configuración'!B14 -> TI | C10: ='1. Configuración'!G14 -> Sí | D10: ='1. Configuración'!F14 -> 0.055 | E10: =IF(AND(C10="Sí",B10<>"Comisiones"),D10,0) -> 0.055 | F10: =IF(B10="Comisiones",$F$3,IF($C$17=0,0,$F$4*(E10/$C$17))) -> 5145161.3 | G10: =F10/12 -> 428763.44
B11: ='1. Configuración'!B15 -> Marketing | C11: ='1. Configuración'!G15 -> Sí | D11: ='1. Configuración'!F15 -> 0.125 | E11: =IF(AND(C11="Sí",B11<>"Comisiones"),D11,0) -> 0.125 | F11: =IF(B11="Comisiones",$F$3,IF($C$17=0,0,$F$4*(E11/$C$17))) -> 11693548 | G11: =F11/12 -> 974462.37
B12: ='1. Configuración'!B16 -> RH | C12: ='1. Configuración'!G16 -> Sí | D12: ='1. Configuración'!F16 -> 0.04 | E12: =IF(AND(C12="Sí",B12<>"Comisiones"),D12,0) -> 0.04 | F12: =IF(B12="Comisiones",$F$3,IF($C$17=0,0,$F$4*(E12/$C$17))) -> 3741935.5 | G12: =F12/12 -> 311827.96
B13: ='1. Configuración'!B17 -> Admin | C13: ='1. Configuración'!G17 -> Sí | D13: ='1. Configuración'!F17 -> 0.04 | E13: =IF(AND(C13="Sí",B13<>"Comisiones"),D13,0) -> 0.04 | F13: =IF(B13="Comisiones",$F$3,IF($C$17=0,0,$F$4*(E13/$C$17))) -> 3741935.5 | G13: =F13/12 -> 311827.96
B14: ='1. Configuración'!B18 -> Comisiones | C14: ='1. Configuración'!G18 -> Sí | D14: ='1. Configuración'!F18 -> 0.02 | E14: =IF(AND(C14="Sí",B14<>"Comisiones"),D14,0) -> 0 | F14: =IF(B14="Comisiones",$F$3,IF($C$17=0,0,$F$4*(E14/$C$17))) -> 1000000 | G14: =F14/12 -> 83333.333
B15: ='1. Configuración'!B19 -> Logística | C15: ='1. Configuración'!G19 -> No | D15: ='1. Configuración'!F19 -> 0.06 | E15: =IF(AND(C15="Sí",B15<>"Comisiones"),D15,0) -> 0 | F15: =IF(B15="Comisiones",$F$3,IF($C$17=0,0,$F$4*(E15/$C$17))) -> 0 | G15: =F15/12 -> 0
B16: ='1. Configuración'!B20 -> Construcción | C16: ='1. Configuración'!G20 -> No | D16: ='1. Configuración'!F20 -> 0.035 | E16: =IF(AND(C16="Sí",B16<>"Comisiones"),D16,0) -> 0 | F16: =IF(B16="Comisiones",$F$3,IF($C$17=0,0,$F$4*(E16/$C$17))) -> 0 | G16: =F16/12 -> 0
B17: Suma pesos activos (sin comisiones) | C17: =SUM(E8:E16) -> 0.31
B19: Montos mensuales (ajustados por FE)
B20: Servicio | C20: Ene | D20: Feb | E20: Mar | F20: Abr | G20: May | H20: Jun | I20: Jul | J20: Ago | K20: Sep | L20: Oct | M20: Nov | N20: Dic | O20: Total anual
B21: =B8 -> Legal | C21: =IF(C8="Sí",G8*'2. Estacionalidad'!D7,0) -> 155913.98 | D21: =IF(C8="Sí",G8*'2. Estacionalidad'!D8,0) -> 155913.98 | E21: =IF(C8="Sí",G8*'2. Estacionalidad'!D9,0) -> 155913.98 | F21: =IF(C8="Sí",G8*'2. Estacionalidad'!D10,0) -> 155913.98 | G21: =IF(C8="Sí",G8*'2. Estacionalidad'!D11,0) -> 155913.98 | H21: =IF(C8="Sí",G8*'2. Estacionalidad'!D12,0) -> 155913.98 | I21: =IF(C8="Sí",G8*'2. Estacionalidad'!D13,0) -> 155913.98 | J21: =IF(C8="Sí",G8*'2. Estacionalidad'!D14,0) -> 155913.98 | K21: =IF(C8="Sí",G8*'2. Estacionalidad'!D15,0) -> 155913.98 | L21: =IF(C8="Sí",G8*'2. Estacionalidad'!D16,0) -> 155913.98 | M21: =IF(C8="Sí",G8*'2. Estacionalidad'!D17,0) -> 155913.98 | N21: =IF(C8="Sí",G8*'2. Estacionalidad'!D18,0) -> 155913.98 | O21: =SUM(C21:N21) -> 1870967.7
B22: =B9 -> Contable | C22: =IF(C9="Sí",G9*'2. Estacionalidad'!D7,0) -> 233870.97 | D22: =IF(C9="Sí",G9*'2. Estacionalidad'!D8,0) -> 233870.97 | E22: =IF(C9="Sí",G9*'2. Estacionalidad'!D9,0) -> 233870.97 | F22: =IF(C9="Sí",G9*'2. Estacionalidad'!D10,0) -> 233870.97 | G22: =IF(C9="Sí",G9*'2. Estacionalidad'!D11,0) -> 233870.97 | H22: =IF(C9="Sí",G9*'2. Estacionalidad'!D12,0) -> 233870.97 | I22: =IF(C9="Sí",G9*'2. Estacionalidad'!D13,0) -> 233870.97 | J22: =IF(C9="Sí",G9*'2. Estacionalidad'!D14,0) -> 233870.97 | K22: =IF(C9="Sí",G9*'2. Estacionalidad'!D15,0) -> 233870.97 | L22: =IF(C9="Sí",G9*'2. Estacionalidad'!D16,0) -> 233870.97 | M22: =IF(C9="Sí",G9*'2. Estacionalidad'!D17,0) -> 233870.97 | N22: =IF(C9="Sí",G9*'2. Estacionalidad'!D18,0) -> 233870.97 | O22: =SUM(C22:N22) -> 2806451.6
B23: =B10 -> TI | C23: =IF(C10="Sí",G10*'2. Estacionalidad'!D7,0) -> 428763.44 | D23: =IF(C10="Sí",G10*'2. Estacionalidad'!D8,0) -> 428763.44 | E23: =IF(C10="Sí",G10*'2. Estacionalidad'!D9,0) -> 428763.44 | F23: =IF(C10="Sí",G10*'2. Estacionalidad'!D10,0) -> 428763.44 | G23: =IF(C10="Sí",G10*'2. Estacionalidad'!D11,0) -> 428763.44 | H23: =IF(C10="Sí",G10*'2. Estacionalidad'!D12,0) -> 428763.44 | I23: =IF(C10="Sí",G10*'2. Estacionalidad'!D13,0) -> 428763.44 | J23: =IF(C10="Sí",G10*'2. Estacionalidad'!D14,0) -> 428763.44 | K23: =IF(C10="Sí",G10*'2. Estacionalidad'!D15,0) -> 428763.44 | L23: =IF(C10="Sí",G10*'2. Estacionalidad'!D16,0) -> 428763.44 | M23: =IF(C10="Sí",G10*'2. Estacionalidad'!D17,0) -> 428763.44 | N23: =IF(C10="Sí",G10*'2. Estacionalidad'!D18,0) -> 428763.44 | O23: =SUM(C23:N23) -> 5145161.3
B24: =B11 -> Marketing | C24: =IF(C11="Sí",G11*'2. Estacionalidad'!D7,0) -> 974462.37 | D24: =IF(C11="Sí",G11*'2. Estacionalidad'!D8,0) -> 974462.37 | E24: =IF(C11="Sí",G11*'2. Estacionalidad'!D9,0) -> 974462.37 | F24: =IF(C11="Sí",G11*'2. Estacionalidad'!D10,0) -> 974462.37 | G24: =IF(C11="Sí",G11*'2. Estacionalidad'!D11,0) -> 974462.37 | H24: =IF(C11="Sí",G11*'2. Estacionalidad'!D12,0) -> 974462.37 | I24: =IF(C11="Sí",G11*'2. Estacionalidad'!D13,0) -> 974462.37 | J24: =IF(C11="Sí",G11*'2. Estacionalidad'!D14,0) -> 974462.37 | K24: =IF(C11="Sí",G11*'2. Estacionalidad'!D15,0) -> 974462.37 | L24: =IF(C11="Sí",G11*'2. Estacionalidad'!D16,0) -> 974462.37 | M24: =IF(C11="Sí",G11*'2. Estacionalidad'!D17,0) -> 974462.37 | N24: =IF(C11="Sí",G11*'2. Estacionalidad'!D18,0) -> 974462.37 | O24: =SUM(C24:N24) -> 11693548
B25: =B12 -> RH | C25: =IF(C12="Sí",G12*'2. Estacionalidad'!D7,0) -> 311827.96 | D25: =IF(C12="Sí",G12*'2. Estacionalidad'!D8,0) -> 311827.96 | E25: =IF(C12="Sí",G12*'2. Estacionalidad'!D9,0) -> 311827.96 | F25: =IF(C12="Sí",G12*'2. Estacionalidad'!D10,0) -> 311827.96 | G25: =IF(C12="Sí",G12*'2. Estacionalidad'!D11,0) -> 311827.96 | H25: =IF(C12="Sí",G12*'2. Estacionalidad'!D12,0) -> 311827.96 | I25: =IF(C12="Sí",G12*'2. Estacionalidad'!D13,0) -> 311827.96 | J25: =IF(C12="Sí",G12*'2. Estacionalidad'!D14,0) -> 311827.96 | K25: =IF(C12="Sí",G12*'2. Estacionalidad'!D15,0) -> 311827.96 | L25: =IF(C12="Sí",G12*'2. Estacionalidad'!D16,0) -> 311827.96 | M25: =IF(C12="Sí",G12*'2. Estacionalidad'!D17,0) -> 311827.96 | N25: =IF(C12="Sí",G12*'2. Estacionalidad'!D18,0) -> 311827.96 | O25: =SUM(C25:N25) -> 3741935.5
B26: =B13 -> Admin | C26: =IF(C13="Sí",G13*'2. Estacionalidad'!D7,0) -> 311827.96 | D26: =IF(C13="Sí",G13*'2. Estacionalidad'!D8,0) -> 311827.96 | E26: =IF(C13="Sí",G13*'2. Estacionalidad'!D9,0) -> 311827.96 | F26: =IF(C13="Sí",G13*'2. Estacionalidad'!D10,0) -> 311827.96 | G26: =IF(C13="Sí",G13*'2. Estacionalidad'!D11,0) -> 311827.96 | H26: =IF(C13="Sí",G13*'2. Estacionalidad'!D12,0) -> 311827.96 | I26: =IF(C13="Sí",G13*'2. Estacionalidad'!D13,0) -> 311827.96 | J26: =IF(C13="Sí",G13*'2. Estacionalidad'!D14,0) -> 311827.96 | K26: =IF(C13="Sí",G13*'2. Estacionalidad'!D15,0) -> 311827.96 | L26: =IF(C13="Sí",G13*'2. Estacionalidad'!D16,0) -> 311827.96 | M26: =IF(C13="Sí",G13*'2. Estacionalidad'!D17,0) -> 311827.96 | N26: =IF(C13="Sí",G13*'2. Estacionalidad'!D18,0) -> 311827.96 | O26: =SUM(C26:N26) -> 3741935.5
B27: =B14 -> Comisiones | C27: =IF(C14="Sí",'2. Estacionalidad'!C7*$C$5,0) -> 83333.333 | D27: =IF(C14="Sí",'2. Estacionalidad'!C8*$C$5,0) -> 83333.333 | E27: =IF(C14="Sí",'2. Estacionalidad'!C9*$C$5,0) -> 83333.333 | F27: =IF(C14="Sí",'2. Estacionalidad'!C10*$C$5,0) -> 83333.333 | G27: =IF(C14="Sí",'2. Estacionalidad'!C11*$C$5,0) -> 83333.333 | H27: =IF(C14="Sí",'2. Estacionalidad'!C12*$C$5,0) -> 83333.333 | I27: =IF(C14="Sí",'2. Estacionalidad'!C13*$C$5,0) -> 83333.333 | J27: =IF(C14="Sí",'2. Estacionalidad'!C14*$C$5,0) -> 83333.333 | K27: =IF(C14="Sí",'2. Estacionalidad'!C15*$C$5,0) -> 83333.333 | L27: =IF(C14="Sí",'2. Estacionalidad'!C16*$C$5,0) -> 83333.333 | M27: =IF(C14="Sí",'2. Estacionalidad'!C17*$C$5,0) -> 83333.333 | N27: =IF(C14="Sí",'2. Estacionalidad'!C18*$C$5,0) -> 83333.333 | O27: =SUM(C27:N27) -> 1000000
B28: =B15 -> Logística | C28: =IF(C15="Sí",G15*'2. Estacionalidad'!D7,0) -> 0 | D28: =IF(C15="Sí",G15*'2. Estacionalidad'!D8,0) -> 0 | E28: =IF(C15="Sí",G15*'2. Estacionalidad'!D9,0) -> 0 | F28: =IF(C15="Sí",G15*'2. Estacionalidad'!D10,0) -> 0 | G28: =IF(C15="Sí",G15*'2. Estacionalidad'!D11,0) -> 0 | H28: =IF(C15="Sí",G15*'2. Estacionalidad'!D12,0) -> 0 | I28: =IF(C15="Sí",G15*'2. Estacionalidad'!D13,0) -> 0 | J28: =IF(C15="Sí",G15*'2. Estacionalidad'!D14,0) -> 0 | K28: =IF(C15="Sí",G15*'2. Estacionalidad'!D15,0) -> 0 | L28: =IF(C15="Sí",G15*'2. Estacionalidad'!D16,0) -> 0 | M28: =IF(C15="Sí",G15*'2. Estacionalidad'!D17,0) -> 0 | N28: =IF(C15="Sí",G15*'2. Estacionalidad'!D18,0) -> 0 | O28: =SUM(C28:N28) -> 0
B29: =B16 -> Construcción | C29: =IF(C16="Sí",G16*'2. Estacionalidad'!D7,0) -> 0 | D29: =IF(C16="Sí",G16*'2. Estacionalidad'!D8,0) -> 0 | E29: =IF(C16="Sí",G16*'2. Estacionalidad'!D9,0) -> 0 | F29: =IF(C16="Sí",G16*'2. Estacionalidad'!D10,0) -> 0 | G29: =IF(C16="Sí",G16*'2. Estacionalidad'!D11,0) -> 0 | H29: =IF(C16="Sí",G16*'2. Estacionalidad'!D12,0) -> 0 | I29: =IF(C16="Sí",G16*'2. Estacionalidad'!D13,0) -> 0 | J29: =IF(C16="Sí",G16*'2. Estacionalidad'!D14,0) -> 0 | K29: =IF(C16="Sí",G16*'2. Estacionalidad'!D15,0) -> 0 | L29: =IF(C16="Sí",G16*'2. Estacionalidad'!D16,0) -> 0 | M29: =IF(C16="Sí",G16*'2. Estacionalidad'!D17,0) -> 0 | N29: =IF(C16="Sí",G16*'2. Estacionalidad'!D18,0) -> 0 | O29: =SUM(C29:N29) -> 0
B30: TOTAL | C30: =SUM(C21:C29) -> 2500000 | D30: =SUM(D21:D29) -> 2500000 | E30: =SUM(E21:E29) -> 2500000 | F30: =SUM(F21:F29) -> 2500000 | G30: =SUM(G21:G29) -> 2500000 | H30: =SUM(H21:H29) -> 2500000 | I30: =SUM(I21:I29) -> 2500000 | J30: =SUM(J21:J29) -> 2500000 | ... O30: =SUM(O21:O29) -> 30000000

Sheet 4. Facturación
B1: Plan Detallado de Facturación (Operativo)
B3: Cliente | C3: ='1. Configuración'!C3 -> Acme SA de CV
B5: Servicio | C5: Campo manual | D5: Contenido | E5: Ene | F5: Feb | G5: Mar | H5: Abr | I5: May | J5: Jun | K5: Jul | L5: Ago | M5: Sep | N5: Oct | O5: Nov | P5: Dic
B6: Legal | C6: Concepto del Servicio a Prestar
C7: Clave/Concepto SAT para Facturación
C8: Montos mensuales (MXN) | D8: Vinculado | E8: ='3. Matriz Proyección'!C21 -> 155913.98 | F8: ='3. Matriz Proyección'!D21 -> 155913.98 | G8: ='3. Matriz Proyección'!E21 -> 155913.98 | H8: ='3. Matriz Proyección'!F21 -> 155913.98 | I8: ='3. Matriz Proyección'!G21 -> 155913.98 | J8: ='3. Matriz Proyección'!H21 -> 155913.98 | K8: ='3. Matriz Proyección'!I21 -> 155913.98 | L8: ='3. Matriz Proyección'!J21 -> 155913.98 | ... P8: ='3. Matriz Proyección'!N21 -> 155913.98
B10: Contable | C10: Concepto del Servicio a Prestar
C11: Clave/Concepto SAT para Facturación
C12: Montos mensuales (MXN) | D12: Vinculado | E12: ='3. Matriz Proyección'!C22 -> 233870.97 | F12: ='3. Matriz Proyección'!D22 -> 233870.97 | G12: ='3. Matriz Proyección'!E22 -> 233870.97 | H12: ='3. Matriz Proyección'!F22 -> 233870.97 | I12: ='3. Matriz Proyección'!G22 -> 233870.97 | J12: ='3. Matriz Proyección'!H22 -> 233870.97 | K12: ='3. Matriz Proyección'!I22 -> 233870.97 | L12: ='3. Matriz Proyección'!J22 -> 233870.97 | ... P12: ='3. Matriz Proyección'!N22 -> 233870.97
B14: TI | C14: Concepto del Servicio a Prestar
C15: Clave/Concepto SAT para Facturación
C16: Montos mensuales (MXN) | D16: Vinculado | E16: ='3. Matriz Proyección'!C23 -> 428763.44 | F16: ='3. Matriz Proyección'!D23 -> 428763.44 | G16: ='3. Matriz Proyección'!E23 -> 428763.44 | H16: ='3. Matriz Proyección'!F23 -> 428763.44 | I16: ='3. Matriz Proyección'!G23 -> 428763.44 | J16: ='3. Matriz Proyección'!H23 -> 428763.44 | K16: ='3. Matriz Proyección'!I23 -> 428763.44 | L16: ='3. Matriz Proyección'!J23 -> 428763.44 | ... P16: ='3. Matriz Proyección'!N23 -> 428763.44
B18: Marketing | C18: Concepto del Servicio a Prestar
C19: Clave/Concepto SAT para Facturación
C20: Montos mensuales (MXN) | D20: Vinculado | E20: ='3. Matriz Proyección'!C24 -> 974462.37 | F20: ='3. Matriz Proyección'!D24 -> 974462.37 | G20: ='3. Matriz Proyección'!E24 -> 974462.37 | H20: ='3. Matriz Proyección'!F24 -> 974462.37 | I20: ='3. Matriz Proyección'!G24 -> 974462.37 | J20: ='3. Matriz Proyección'!H24 -> 974462.37 | K20: ='3. Matriz Proyección'!I24 -> 974462.37 | L20: ='3. Matriz Proyección'!J24 -> 974462.37 | ... P20: ='3. Matriz Proyección'!N24 -> 974462.37
B22: RH | C22: Concepto del Servicio a Prestar
C23: Clave/Concepto SAT para Facturación
C24: Montos mensuales (MXN) | D24: Vinculado | E24: ='3. Matriz Proyección'!C25 -> 311827.96 | F24: ='3. Matriz Proyección'!D25 -> 311827.96 | G24: ='3. Matriz Proyección'!E25 -> 311827.96 | H24: ='3. Matriz Proyección'!F25 -> 311827.96 | I24: ='3. Matriz Proyección'!G25 -> 311827.96 | J24: ='3. Matriz Proyección'!H25 -> 311827.96 | K24: ='3. Matriz Proyección'!I25 -> 311827.96 | L24: ='3. Matriz Proyección'!J25 -> 311827.96 | ... P24: ='3. Matriz Proyección'!N25 -> 311827.96
B26: Admin | C26: Concepto del Servicio a Prestar
C27: Clave/Concepto SAT para Facturación
C28: Montos mensuales (MXN) | D28: Vinculado | E28: ='3. Matriz Proyección'!C26 -> 311827.96 | F28: ='3. Matriz Proyección'!D26 -> 311827.96 | G28: ='3. Matriz Proyección'!E26 -> 311827.96 | H28: ='3. Matriz Proyección'!F26 -> 311827.96 | I28: ='3. Matriz Proyección'!G26 -> 311827.96 | J28: ='3. Matriz Proyección'!H26 -> 311827.96 | K28: ='3. Matriz Proyección'!I26 -> 311827.96 | L28: ='3. Matriz Proyección'!J26 -> 311827.96 | ... P28: ='3. Matriz Proyección'!N26 -> 311827.96
B30: Comisiones | C30: Concepto del Servicio a Prestar
C31: Clave/Concepto SAT para Facturación
C32: Montos mensuales (MXN) | D32: Vinculado | E32: ='3. Matriz Proyección'!C27 -> 83333.333 | F32: ='3. Matriz Proyección'!D27 -> 83333.333 | G32: ='3. Matriz Proyección'!E27 -> 83333.333 | H32: ='3. Matriz Proyección'!F27 -> 83333.333 | I32: ='3. Matriz Proyección'!G27 -> 83333.333 | J32: ='3. Matriz Proyección'!H27 -> 83333.333 | K32: ='3. Matriz Proyección'!I27 -> 83333.333 | L32: ='3. Matriz Proyección'!J27 -> 83333.333 | ... P32: ='3. Matriz Proyección'!N27 -> 83333.333
B34: Logística | C34: Concepto del Servicio a Prestar
C35: Clave/Concepto SAT para Facturación
C36: Montos mensuales (MXN) | D36: Vinculado | E36: ='3. Matriz Proyección'!C28 -> 0 | F36: ='3. Matriz Proyección'!D28 -> 0 | G36: ='3. Matriz Proyección'!E28 -> 0 | H36: ='3. Matriz Proyección'!F28 -> 0 | I36: ='3. Matriz Proyección'!G28 -> 0 | J36: ='3. Matriz Proyección'!H28 -> 0 | K36: ='3. Matriz Proyección'!I28 -> 0 | L36: ='3. Matriz Proyección'!J28 -> 0 | ... P36: ='3. Matriz Proyección'!N28 -> 0
B38: Construcción | C38: Concepto del Servicio a Prestar
C39: Clave/Concepto SAT para Facturación
C40: Montos mensuales (MXN) | D40: Vinculado | E40: ='3. Matriz Proyección'!C29 -> 0 | F40: ='3. Matriz Proyección'!D29 -> 0 | G40: ='3. Matriz Proyección'!E29 -> 0 | H40: ='3. Matriz Proyección'!F29 -> 0 | I40: ='3. Matriz Proyección'!G29 -> 0 | J40: ='3. Matriz Proyección'!H29 -> 0 | K40: ='3. Matriz Proyección'!I29 -> 0 | L40: ='3. Matriz Proyección'!J29 -> 0 | ... P40: ='3. Matriz Proyección'!N29 -> 0
B42: TOTAL MENSUAL | C42: Suma de montos | E42: =SUM(E8,E12,E16,E20,E24,E28,E32,E36,E40) -> 2500000 | F42: =SUM(F8,F12,F16,F20,F24,F28,F32,F36,F40) -> 2500000 | G42: =SUM(G8,G12,G16,G20,G24,G28,G32,G36,G40) -> 2500000 | H42: =SUM(H8,H12,H16,H20,H24,H28,H32,H36,H40) -> 2500000 | I42: =SUM(I8,I12,I16,I20,I24,I28,I32,I36,I40) -> 2500000 | J42: =SUM(J8,J12,J16,J20,J24,J28,J32,J36,J40) -> 2500000 | K42: =SUM(K8,K12,K16,K20,K24,K28,K32,K36,K40) -> 2500000 | L42: =SUM(L8,L12,L16,L20,L24,L28,L32,L36,L40) -> 2500000 | ... P42: =SUM(P8,P12,P16,P20,P24,P28,P32,P36,P40) -> 2500000

Sheet 5. Dashboard
B1: Dashboard Resumen
B2: Resumen: compara la curva de pagos (servicios) contra ventas y el presupuesto mensual promedio.
B3: Mes | C3: Ventas | D3: Pago total (servicios) | E3: Diferencia (Pago - Presupuesto/12)
B4: Ene | C4: ='2. Estacionalidad'!C7 -> 4166666.7 | D4: ='3. Matriz Proyección'!C30 -> 2500000 | E4: =D4-('1. Configuración'!C5/12) -> 0
B5: Feb | C5: ='2. Estacionalidad'!C8 -> 4166666.7 | D5: ='3. Matriz Proyección'!D30 -> 2500000 | E5: =D5-('1. Configuración'!C5/12) -> 0
B6: Mar | C6: ='2. Estacionalidad'!C9 -> 4166666.7 | D6: ='3. Matriz Proyección'!E30 -> 2500000 | E6: =D6-('1. Configuración'!C5/12) -> 0
B7: Abr | C7: ='2. Estacionalidad'!C10 -> 4166666.7 | D7: ='3. Matriz Proyección'!F30 -> 2500000 | E7: =D7-('1. Configuración'!C5/12) -> 0
B8: May | C8: ='2. Estacionalidad'!C11 -> 4166666.7 | D8: ='3. Matriz Proyección'!G30 -> 2500000 | E8: =D8-('1. Configuración'!C5/12) -> 0
B9: Jun | C9: ='2. Estacionalidad'!C12 -> 4166666.7 | D9: ='3. Matriz Proyección'!H30 -> 2500000 | E9: =D9-('1. Configuración'!C5/12) -> 0
B10: Jul | C10: ='2. Estacionalidad'!C13 -> 4166666.7 | D10: ='3. Matriz Proyección'!I30 -> 2500000 | E10: =D10-('1. Configuración'!C5/12) -> 0
B11: Ago | C11: ='2. Estacionalidad'!C14 -> 4166666.7 | D11: ='3. Matriz Proyección'!J30 -> 2500000 | E11: =D11-('1. Configuración'!C5/12) -> 0
B12: Sep | C12: ='2. Estacionalidad'!C15 -> 4166666.7 | D12: ='3. Matriz Proyección'!K30 -> 2500000 | E12: =D12-('1. Configuración'!C5/12) -> 0
B13: Oct | C13: ='2. Estacionalidad'!C16 -> 4166666.7 | D13: ='3. Matriz Proyección'!L30 -> 2500000 | E13: =D13-('1. Configuración'!C5/12) -> 0
B14: Nov | C14: ='2. Estacionalidad'!C17 -> 4166666.7 | D14: ='3. Matriz Proyección'!M30 -> 2500000 | E14: =D14-('1. Configuración'!C5/12) -> 0
B15: Dic | C15: ='2. Estacionalidad'!C18 -> 4166666.7 | D15: ='3. Matriz Proyección'!N30 -> 2500000 | E15: =D15-('1. Configuración'!C5/12) -> 0
B16: TOTAL | C16: =SUM(C4:C15) -> 50000000 | D16: =SUM(D4:D15) -> 30000000 | E16: =SUM(E4:E15) -> 0
